solarlib/__init__.py
solarlib/calendar.py
solarlib/error_handling.py
solarlib/location.py
solarlib/solar.py
solarlib/utils.py
tests/__init__.py
tests/test_calendar.py
solarlib-0.1.0.dist-info/LICENSE.txt
solarlib-0.1.0.dist-info/METADATA
solarlib-0.1.0.dist-info/WHEEL
solarlib-0.1.0.dist-info/top_level.txt
solarlib-0.1.0.dist-info/RECORD
